olchikipython/__init__.py
olchikipython/olchiki_python.py
olchikipython/filters/__init__.py
olchikipython/filters/pycnnun.py
olchikipython/filters/unidecoder.py
olchikipython/languages/__init__.py
olchikipython/languages/ol/__init__.py
olchikipython/languages/ol/ol_native.lang.yaml
olchikipython/languages/ol/ol_native_2.lang.yaml
olchikipython/modes/__init__.py
olchikipython/modes/dirty.py
olchikipython/modes/dirty_v2.py
olchikipython/modes/lex.py
olchikipython/samples/__init__.py
olchikipython/samples/en/__init__.py
olchikipython/samples/en/conditionals.py
olchikipython/samples/ol/__init__.py
olchikipython/samples/ol/main.ol.py
olchikipython-0.0.2.dist-info/METADATA
olchikipython-0.0.2.dist-info/WHEEL
olchikipython-0.0.2.dist-info/entry_points.txt
olchikipython-0.0.2.dist-info/top_level.txt
olchikipython-0.0.2.dist-info/RECORD
