Metadata-Version: 2.1
Name: olchikipython
Version: 0.0.2
Requires-Dist: ply
Requires-Dist: PyYAML
Requires-Dist: Unidecode
